sharedmutexwin.cp311-win_amd64.pyd
sharedmutexwin-2.0.0.dist-info/METADATA
sharedmutexwin-2.0.0.dist-info/WHEEL
sharedmutexwin-2.0.0.dist-info/top_level.txt
sharedmutexwin-2.0.0.dist-info/RECORD
